setup.py
facebot/__init__.py
facebot/message.py
facebot/sticker.py
facebot.egg-info/PKG-INFO
facebot.egg-info/SOURCES.txt
facebot.egg-info/dependency_links.txt
facebot.egg-info/requires.txt
facebot.egg-info/top_level.txt