Metadata-Version: 1.0
Name: facebot
Version: 0.0.8
Summary: Unofficial facebook api
Home-page: https://github.com/davidyen1124/Facebot
Author: davidyen1124
Author-email: davidyen1124@gmail.com
License: MIT
Platform: UNKNOWN
